vallex/__init__.py
vallex/data/__init__.py
vallex/data/collation.py
vallex/data/datamodule.py
vallex/data/dataset.py
vallex/data/fbank.py
vallex/data/input_strategies.py
vallex/data/tokenizer.py
vallex/models/__init__.py
vallex/models/macros.py
vallex/models/transformer.py
vallex/models/vallex.py
vallex/models/visualizer.py
vallex/modules/__init__.py
vallex/modules/activation.py
vallex/modules/embedding.py
vallex/modules/optim.py
vallex/modules/scaling.py
vallex/modules/scheduler.py
vallex/modules/transformer.py
vallex/utils/__init__.py
vallex/utils/download.py
vallex/utils/generation.py
vallex/utils/macros.py
vallex/utils/prompt_making.py
vallex/utils/sentence_cutter.py
vallex/utils/symbol_table.py
vallex/utils/g2p/__init__.py
vallex/utils/g2p/cleaners.py
vallex/utils/g2p/english.py
vallex/utils/g2p/japanese.py
vallex/utils/g2p/mandarin.py
vallex/utils/g2p/symbols.py
VALL_E_X-0.0.0.dist-info/LICENSE
VALL_E_X-0.0.0.dist-info/METADATA
VALL_E_X-0.0.0.dist-info/WHEEL
VALL_E_X-0.0.0.dist-info/dependency_links.txt
VALL_E_X-0.0.0.dist-info/top_level.txt
VALL_E_X-0.0.0.dist-info/RECORD
